README.md
setup.py
jc_pytools.egg-info/PKG-INFO
jc_pytools.egg-info/SOURCES.txt
jc_pytools.egg-info/dependency_links.txt
jc_pytools.egg-info/top_level.txt
jctools/__init__.py
jctools/tools.py