Metadata-Version: 2.1
Name: jc-pytools
Version: 1.0.1
Summary: Simple everyday Python tools.
Home-page: https://bitbucket.org/calvertjadon/jcpytools/
Author: Jadon Calvert
Author-email: calvertjadon@gmail.com
License: MIT
Platform: UNKNOWN
